.gitattributes
.gitignore
LICENSE.txt
MANIFEST.in
README.md
isoCycle_yourData_Colab.ipynb
prepare_release.py
setup.py
isoCycle/__init__.py
isoCycle/decoder.py
isoCycle/spike.py
isoCycle/utility.py
isoCycle/version.py
isoCycle.egg-info/PKG-INFO
isoCycle.egg-info/SOURCES.txt
isoCycle.egg-info/dependency_links.txt
isoCycle.egg-info/requires.txt
isoCycle.egg-info/top_level.txt
isoCycle/__pycache__/__init__.cpython-310.pyc
isoCycle/__pycache__/__init__.cpython-38.pyc
isoCycle/__pycache__/__init__.cpython-39.pyc
isoCycle/__pycache__/_version.cpython-39.pyc
isoCycle/__pycache__/decoder.cpython-310.pyc
isoCycle/__pycache__/decoder.cpython-38.pyc
isoCycle/__pycache__/decoder.cpython-39.pyc
isoCycle/__pycache__/decoder.cpython-39.pyc.1937786954064
isoCycle/__pycache__/decoder.cpython-39.pyc.1944978299760
isoCycle/__pycache__/isoCycle.cpython-39.pyc
isoCycle/__pycache__/spike.cpython-38.pyc
isoCycle/__pycache__/spike.cpython-39.pyc
isoCycle/__pycache__/utility.cpython-38.pyc
isoCycle/__pycache__/utility.cpython-39.pyc
isoCycle/example/README.md
isoCycle/example/isoCycle_example.ipynb
isoCycle/example/spikesTimes.npy
isoCycle/example/stimTimes.pkl
isoCycle/example/.ipynb_checkpoints/isoCycle_example-checkpoint.ipynb
isoCycle/files/Thumbs.db
isoCycle/files/decoder_schematics.jpg
isoCycle/files/gammaCycleAvgShape.png
isoCycle/files/isoCycleInput_build.m
isoCycle/model/isoCycle_publishedModel_2022-06-28.h5
isoCycle/model/isoCycle_publishedModel_2022-06-28.pkl