Metadata-Version: 2.1
Name: isoCycle
Version: 0.1.15
Summary: isolating single cycles of oscillatory activity in neuronal spiking
Home-page: https://github.com/esiabri/isoCycle
Download-URL: https://github.com/esiabri/isoCycle/archive/refs/tags/0.1.1.tar.gz
Author: Ehsan Sabri
Author-email: ehsan.sabri@gmail.com
License: CC-BY-NC-SA-4.0
Keywords: Neuroscience,Oscillation,Cycle
Classifier: Development Status :: 3 - Alpha
Classifier: Intended Audience :: Science/Research
Classifier: Programming Language :: Python
License-File: LICENSE.txt
